{
  "Heading": {
    "as": {
      "type": "As",
      "description": "The HTML element to render.",
      "required": false
    },
    "asChild": {
      "type": "boolean",
      "description": "Merges its props onto its immediate child.",
      "required": false
    },
    "css": {
      "type": "CSSObject | CSSObject[]",
      "description": "The CSS object.",
      "required": false
    },
    "colorScheme": {
      "type": "\"amber\" | \"black\" | \"blackAlpha\" | \"blue\" | \"cyan\" | \"danger\" | \"emerald\" | \"error\" | \"flashy\" | \"fuchsia\" ...",
      "description": "Set color scheme variables.",
      "required": false
    },
    "size": {
      "type": "\"2xl\" | \"3xl\" | \"4xl\" | \"5xl\" | \"6xl\" | \"7xl\" | \"8xl\" | \"9xl\" | \"lg\" | \"md\" ...",
      "defaultValue": "\"4xl\"",
      "description": "The size of the component.",
      "required": false
    }
  }
}
