{
  "AlertDescription": {},
  "AlertIcon": {
    "variant": {
      "type": "type ONLY_FOR_FORMAT =\n  | \"grid\"\n  | \"audio\"\n  | \"circles\"\n  | \"dots\"\n  | \"oval\"\n  | \"puff\"\n  | \"rings\"",
      "required": false
    }
  },
  "Alert": {
    "colorScheme": {
      "type": "\"blackAlpha\" | \"whiteAlpha\" | \"amber\" | \"blue\" | \"info\" | \"link\" | \"primary\" | \"cyan\" | \"emerald\" | \"flashy\" | \"fuchsia\" | \"gray\" | \"green\" | \"success\" | \"indigo\" | \"lime\" | \"neutral\" | \"orange\" | \"warning\" | \"pink\" | \"purple\" | \"red\" | \"danger\" | \"rose\" | \"sky\" | \"teal\" | \"violet\" | \"secondary\" | \"yellow\"",
      "defaultValue": "\"primary\"",
      "description": "The visual color appearance of the component.",
      "required": false
    },
    "size": {
      "type": "string",
      "description": "The size of the Alert.",
      "required": false
    },
    "status": {
      "type": "\"info\" | \"success\" | \"warning\" | \"error\" | \"loading\"",
      "defaultValue": "'info'",
      "description": "The status of the alert.",
      "required": false
    },
    "variant": {
      "type": "\"basic\" | \"island-accent\" | \"left-accent\" | \"solid\" | \"subtle\" | \"top-accent\"",
      "defaultValue": "\"basic\"",
      "description": "The variant of the Alert.",
      "required": false
    }
  },
  "AlertTitle": {}
}
